[{"name":"Aitkin","id":"27001","totalVotes":9865,"candidates":[{"id":8639,"name":"Donald Trump","votes":6258},{"id":1036,"name":"Joe Biden","votes":3607}]},{"name":"Anoka","id":"27003","totalVotes":205795,"candidates":[{"id":8639,"name":"Donald Trump","votes":104902},{"id":1036,"name":"Joe Biden","votes":100893}]},{"name":"Becker","id":"27005","totalVotes":19027,"candidates":[{"id":8639,"name":"Donald Trump","votes":12438},{"id":1036,"name":"Joe Biden","votes":6589}]},{"name":"Beltrami","id":"27007","totalVotes":23614,"candidates":[{"id":8639,"name":"Donald Trump","votes":12188},{"id":1036,"name":"Joe Biden","votes":11426}]},{"name":"Benton","id":"27009","totalVotes":21662,"candidates":[{"id":8639,"name":"Donald Trump","votes":14382},{"id":1036,"name":"Joe Biden","votes":7280}]},{"name":"Big Stone","id":"27011","totalVotes":2916,"candidates":[{"id":8639,"name":"Donald Trump","votes":1863},{"id":1036,"name":"Joe Biden","votes":1053}]},{"name":"Blue Earth","id":"27013","totalVotes":35061,"candidates":[{"id":1036,"name":"Joe Biden","votes":18330},{"id":8639,"name":"Donald Trump","votes":16731}]},{"name":"Brown","id":"27015","totalVotes":14305,"candidates":[{"id":8639,"name":"Donald Trump","votes":9552},{"id":1036,"name":"Joe Biden","votes":4753}]},{"name":"Carlton","id":"27017","totalVotes":19889,"candidates":[{"id":1036,"name":"Joe Biden","votes":10098},{"id":8639,"name":"Donald Trump","votes":9791}]},{"name":"Carver","id":"27019","totalVotes":64783,"candidates":[{"id":8639,"name":"Donald Trump","votes":34009},{"id":1036,"name":"Joe Biden","votes":30774}]},{"name":"Cass","id":"27021","totalVotes":17962,"candidates":[{"id":8639,"name":"Donald Trump","votes":11620},{"id":1036,"name":"Joe Biden","votes":6342}]},{"name":"Chippewa","id":"27023","totalVotes":6476,"candidates":[{"id":8639,"name":"Donald Trump","votes":4250},{"id":1036,"name":"Joe Biden","votes":2226}]},{"name":"Chisago","id":"27025","totalVotes":33722,"candidates":[{"id":8639,"name":"Donald Trump","votes":21916},{"id":1036,"name":"Joe Biden","votes":11806}]},{"name":"Clay","id":"27027","totalVotes":31400,"candidates":[{"id":1036,"name":"Joe Biden","votes":16357},{"id":8639,"name":"Donald Trump","votes":15043}]},{"name":"Clearwater","id":"27029","totalVotes":4632,"candidates":[{"id":8639,"name":"Donald Trump","votes":3372},{"id":1036,"name":"Joe Biden","votes":1260}]},{"name":"Cook","id":"27031","totalVotes":3699,"candidates":[{"id":1036,"name":"Joe Biden","votes":2496},{"id":8639,"name":"Donald Trump","votes":1203}]},{"name":"Cottonwood","id":"27033","totalVotes":5999,"candidates":[{"id":8639,"name":"Donald Trump","votes":4165},{"id":1036,"name":"Joe Biden","votes":1834}]},{"name":"Crow Wing","id":"27035","totalVotes":39402,"candidates":[{"id":8639,"name":"Donald Trump","votes":25676},{"id":1036,"name":"Joe Biden","votes":13726}]},{"name":"Dakota","id":"27037","totalVotes":255793,"candidates":[{"id":1036,"name":"Joe Biden","votes":146155},{"id":8639,"name":"Donald Trump","votes":109638}]},{"name":"Dodge","id":"27039","totalVotes":11862,"candidates":[{"id":8639,"name":"Donald Trump","votes":7783},{"id":1036,"name":"Joe Biden","votes":4079}]},{"name":"Douglas","id":"27041","totalVotes":23667,"candidates":[{"id":8639,"name":"Donald Trump","votes":15799},{"id":1036,"name":"Joe Biden","votes":7868}]},{"name":"Faribault","id":"27043","totalVotes":7722,"candidates":[{"id":8639,"name":"Donald Trump","votes":5191},{"id":1036,"name":"Joe Biden","votes":2531}]},{"name":"Fillmore","id":"27045","totalVotes":11852,"candidates":[{"id":8639,"name":"Donald Trump","votes":7301},{"id":1036,"name":"Joe Biden","votes":4551}]},{"name":"Freeborn","id":"27047","totalVotes":16467,"candidates":[{"id":8639,"name":"Donald Trump","votes":9578},{"id":1036,"name":"Joe Biden","votes":6889}]},{"name":"Goodhue","id":"27049","totalVotes":27858,"candidates":[{"id":8639,"name":"Donald Trump","votes":16052},{"id":1036,"name":"Joe Biden","votes":11806}]},{"name":"Grant","id":"27051","totalVotes":3569,"candidates":[{"id":8639,"name":"Donald Trump","votes":2269},{"id":1036,"name":"Joe Biden","votes":1300}]},{"name":"Hennepin","id":"27053","totalVotes":738596,"candidates":[{"id":1036,"name":"Joe Biden","votes":532623},{"id":8639,"name":"Donald Trump","votes":205973}]},{"name":"Houston","id":"27055","totalVotes":11187,"candidates":[{"id":8639,"name":"Donald Trump","votes":6334},{"id":1036,"name":"Joe Biden","votes":4853}]},{"name":"Hubbard","id":"27057","totalVotes":12664,"candidates":[{"id":8639,"name":"Donald Trump","votes":8202},{"id":1036,"name":"Joe Biden","votes":4462}]},{"name":"Isanti","id":"27059","totalVotes":23629,"candidates":[{"id":8639,"name":"Donald Trump","votes":16491},{"id":1036,"name":"Joe Biden","votes":7138}]},{"name":"Itasca","id":"27061","totalVotes":26025,"candidates":[{"id":8639,"name":"Donald Trump","votes":15239},{"id":1036,"name":"Joe Biden","votes":10786}]},{"name":"Jackson","id":"27063","totalVotes":5693,"candidates":[{"id":8639,"name":"Donald Trump","votes":3948},{"id":1036,"name":"Joe Biden","votes":1745}]},{"name":"Kanabec","id":"27065","totalVotes":9052,"candidates":[{"id":8639,"name":"Donald Trump","votes":6278},{"id":1036,"name":"Joe Biden","votes":2774}]},{"name":"Kandiyohi","id":"27067","totalVotes":22877,"candidates":[{"id":8639,"name":"Donald Trump","votes":14437},{"id":1036,"name":"Joe Biden","votes":8440}]},{"name":"Kittson","id":"27069","totalVotes":2552,"candidates":[{"id":8639,"name":"Donald Trump","votes":1546},{"id":1036,"name":"Joe Biden","votes":1006}]},{"name":"Koochiching","id":"27071","totalVotes":6790,"candidates":[{"id":8639,"name":"Donald Trump","votes":4131},{"id":1036,"name":"Joe Biden","votes":2659}]},{"name":"Lac Qui Parle","id":"27073","totalVotes":3974,"candidates":[{"id":8639,"name":"Donald Trump","votes":2528},{"id":1036,"name":"Joe Biden","votes":1446}]},{"name":"Lake","id":"27075","totalVotes":7040,"candidates":[{"id":1036,"name":"Joe Biden","votes":3647},{"id":8639,"name":"Donald Trump","votes":3393}]},{"name":"Lake of the Woods","id":"27077","totalVotes":2375,"candidates":[{"id":8639,"name":"Donald Trump","votes":1704},{"id":1036,"name":"Joe Biden","votes":671}]},{"name":"Le Sueur","id":"27079","totalVotes":16447,"candidates":[{"id":8639,"name":"Donald Trump","votes":10775},{"id":1036,"name":"Joe Biden","votes":5672}]},{"name":"Lincoln","id":"27081","totalVotes":3058,"candidates":[{"id":8639,"name":"Donald Trump","votes":2121},{"id":1036,"name":"Joe Biden","votes":937}]},{"name":"Lyon","id":"27083","totalVotes":12613,"candidates":[{"id":8639,"name":"Donald Trump","votes":7979},{"id":1036,"name":"Joe Biden","votes":4634}]},{"name":"Mahnomen","id":"27087","totalVotes":2254,"candidates":[{"id":8639,"name":"Donald Trump","votes":1142},{"id":1036,"name":"Joe Biden","votes":1112}]},{"name":"Marshall","id":"27089","totalVotes":5016,"candidates":[{"id":8639,"name":"Donald Trump","votes":3721},{"id":1036,"name":"Joe Biden","votes":1295}]},{"name":"Martin","id":"27091","totalVotes":10785,"candidates":[{"id":8639,"name":"Donald Trump","votes":7480},{"id":1036,"name":"Joe Biden","votes":3305}]},{"name":"McLeod","id":"27085","totalVotes":20399,"candidates":[{"id":8639,"name":"Donald Trump","votes":13986},{"id":1036,"name":"Joe Biden","votes":6413}]},{"name":"Meeker","id":"27093","totalVotes":13226,"candidates":[{"id":8639,"name":"Donald Trump","votes":9359},{"id":1036,"name":"Joe Biden","votes":3867}]},{"name":"Mille Lacs","id":"27095","totalVotes":14356,"candidates":[{"id":8639,"name":"Donald Trump","votes":9952},{"id":1036,"name":"Joe Biden","votes":4404}]},{"name":"Morrison","id":"27097","totalVotes":19188,"candidates":[{"id":8639,"name":"Donald Trump","votes":14821},{"id":1036,"name":"Joe Biden","votes":4367}]},{"name":"Mower","id":"27099","totalVotes":18924,"candidates":[{"id":8639,"name":"Donald Trump","votes":10025},{"id":1036,"name":"Joe Biden","votes":8899}]},{"name":"Murray","id":"27101","totalVotes":4812,"candidates":[{"id":8639,"name":"Donald Trump","votes":3363},{"id":1036,"name":"Joe Biden","votes":1449}]},{"name":"Nicollet","id":"27103","totalVotes":18640,"candidates":[{"id":1036,"name":"Joe Biden","votes":9622},{"id":8639,"name":"Donald Trump","votes":9018}]},{"name":"Nobles","id":"27105","totalVotes":8533,"candidates":[{"id":8639,"name":"Donald Trump","votes":5600},{"id":1036,"name":"Joe Biden","votes":2933}]},{"name":"Norman","id":"27107","totalVotes":3357,"candidates":[{"id":8639,"name":"Donald Trump","votes":1953},{"id":1036,"name":"Joe Biden","votes":1404}]},{"name":"Olmsted","id":"27109","totalVotes":89183,"candidates":[{"id":1036,"name":"Joe Biden","votes":49491},{"id":8639,"name":"Donald Trump","votes":39692}]},{"name":"Otter Tail","id":"27111","totalVotes":35758,"candidates":[{"id":8639,"name":"Donald Trump","votes":23800},{"id":1036,"name":"Joe Biden","votes":11958}]},{"name":"Pennington","id":"27113","totalVotes":7100,"candidates":[{"id":8639,"name":"Donald Trump","votes":4532},{"id":1036,"name":"Joe Biden","votes":2568}]},{"name":"Pine","id":"27115","totalVotes":15675,"candidates":[{"id":8639,"name":"Donald Trump","votes":10256},{"id":1036,"name":"Joe Biden","votes":5419}]},{"name":"Pipestone","id":"27117","totalVotes":4859,"candidates":[{"id":8639,"name":"Donald Trump","votes":3553},{"id":1036,"name":"Joe Biden","votes":1306}]},{"name":"Polk","id":"27119","totalVotes":15304,"candidates":[{"id":8639,"name":"Donald Trump","votes":9865},{"id":1036,"name":"Joe Biden","votes":5439}]},{"name":"Pope","id":"27121","totalVotes":6894,"candidates":[{"id":8639,"name":"Donald Trump","votes":4417},{"id":1036,"name":"Joe Biden","votes":2477}]},{"name":"Ramsey","id":"27123","totalVotes":288996,"candidates":[{"id":1036,"name":"Joe Biden","votes":211620},{"id":8639,"name":"Donald Trump","votes":77376}]},{"name":"Red Lake","id":"27125","totalVotes":2145,"candidates":[{"id":8639,"name":"Donald Trump","votes":1454},{"id":1036,"name":"Joe Biden","votes":691}]},{"name":"Redwood","id":"27127","totalVotes":8126,"candidates":[{"id":8639,"name":"Donald Trump","votes":5771},{"id":1036,"name":"Joe Biden","votes":2355}]},{"name":"Renville","id":"27129","totalVotes":7963,"candidates":[{"id":8639,"name":"Donald Trump","votes":5467},{"id":1036,"name":"Joe Biden","votes":2496}]},{"name":"Rice","id":"27131","totalVotes":34866,"candidates":[{"id":8639,"name":"Donald Trump","votes":17464},{"id":1036,"name":"Joe Biden","votes":17402}]},{"name":"Rock","id":"27133","totalVotes":5139,"candidates":[{"id":8639,"name":"Donald Trump","votes":3583},{"id":1036,"name":"Joe Biden","votes":1556}]},{"name":"Roseau","id":"27135","totalVotes":8253,"candidates":[{"id":8639,"name":"Donald Trump","votes":6065},{"id":1036,"name":"Joe Biden","votes":2188}]},{"name":"Scott","id":"27139","totalVotes":85912,"candidates":[{"id":8639,"name":"Donald Trump","votes":45872},{"id":1036,"name":"Joe Biden","votes":40040}]},{"name":"Sherburne","id":"27141","totalVotes":54287,"candidates":[{"id":8639,"name":"Donald Trump","votes":36222},{"id":1036,"name":"Joe Biden","votes":18065}]},{"name":"Sibley","id":"27143","totalVotes":8281,"candidates":[{"id":8639,"name":"Donald Trump","votes":5864},{"id":1036,"name":"Joe Biden","votes":2417}]},{"name":"St. Louis","id":"27137","totalVotes":116721,"candidates":[{"id":1036,"name":"Joe Biden","votes":67704},{"id":8639,"name":"Donald Trump","votes":49017}]},{"name":"Stearns","id":"27145","totalVotes":82838,"candidates":[{"id":8639,"name":"Donald Trump","votes":50959},{"id":1036,"name":"Joe Biden","votes":31879}]},{"name":"Steele","id":"27147","totalVotes":20573,"candidates":[{"id":8639,"name":"Donald Trump","votes":12656},{"id":1036,"name":"Joe Biden","votes":7917}]},{"name":"Stevens","id":"27149","totalVotes":4966,"candidates":[{"id":8639,"name":"Donald Trump","votes":3044},{"id":1036,"name":"Joe Biden","votes":1922}]},{"name":"Swift","id":"27151","totalVotes":5100,"candidates":[{"id":8639,"name":"Donald Trump","votes":3316},{"id":1036,"name":"Joe Biden","votes":1784}]},{"name":"Todd","id":"27153","totalVotes":13039,"candidates":[{"id":8639,"name":"Donald Trump","votes":9753},{"id":1036,"name":"Joe Biden","votes":3286}]},{"name":"Traverse","id":"27155","totalVotes":1833,"candidates":[{"id":8639,"name":"Donald Trump","votes":1172},{"id":1036,"name":"Joe Biden","votes":661}]},{"name":"Wabasha","id":"27157","totalVotes":12849,"candidates":[{"id":8639,"name":"Donald Trump","votes":8153},{"id":1036,"name":"Joe Biden","votes":4696}]},{"name":"Wadena","id":"27159","totalVotes":7543,"candidates":[{"id":8639,"name":"Donald Trump","votes":5520},{"id":1036,"name":"Joe Biden","votes":2023}]},{"name":"Waseca","id":"27161","totalVotes":10120,"candidates":[{"id":8639,"name":"Donald Trump","votes":6624},{"id":1036,"name":"Joe Biden","votes":3496}]},{"name":"Washington","id":"27163","totalVotes":162929,"candidates":[{"id":1036,"name":"Joe Biden","votes":89165},{"id":8639,"name":"Donald Trump","votes":73764}]},{"name":"Watonwan","id":"27165","totalVotes":5090,"candidates":[{"id":8639,"name":"Donald Trump","votes":3103},{"id":1036,"name":"Joe Biden","votes":1987}]},{"name":"Wilkin","id":"27167","totalVotes":3354,"candidates":[{"id":8639,"name":"Donald Trump","votes":2328},{"id":1036,"name":"Joe Biden","votes":1026}]},{"name":"Winona","id":"27169","totalVotes":26560,"candidates":[{"id":1036,"name":"Joe Biden","votes":13333},{"id":8639,"name":"Donald Trump","votes":13227}]},{"name":"Wright","id":"27171","totalVotes":80403,"candidates":[{"id":8639,"name":"Donald Trump","votes":51973},{"id":1036,"name":"Joe Biden","votes":28430}]},{"name":"Yellow Medicine","id":"27173","totalVotes":5422,"candidates":[{"id":8639,"name":"Donald Trump","votes":3734},{"id":1036,"name":"Joe Biden","votes":1688}]}]